leglib/__init__.py
leglib/fmt.py
leglib/legmath.py
leglib/util.py
leglib-old/__init__.py
leglib-old/dxf.py
leglib-old/filesys.py
leglib-old/filters.py
leglib-old/floatdict.py
leglib-old/geom.py
leglib-old/input.py
leglib-old/latex.py
leglib-old/prop.py
leglib-old/reportmaker.py
leglib-old/shapes.py
leglib-old/stack.py
leglib-old/texttbl.py
leglib-old/validate.py
leglib-old/structural/__init__.py
leglib-old/structural/acibars.py
leglib-old/structural/asce7_05.py
leglib-old/structural/asce7_10.py
leglib-old/structural/beamcolumn.py
leglib-old/structural/calc.py
leglib-old/structural/conccol.py
leglib-old/structural/concrete.py
leglib-old/structural/demandcap.py
leglib-old/structural/driftcalc.py
leglib-old/structural/embedment.py
leglib-old/structural/footing.py
leglib-old/structural/frame2d.py
leglib-old/structural/lightpole.py
leglib-old/structural/load_cases.py
leglib-old/structural/piles.py
leglib-old/structural/pit.py
leglib-old/structural/project.py
leglib-old/structural/report.py
leglib-old/structural/retain.py
leglib-old/structural/roof.py
leglib-old/structural/sheetpile.py
leglib-old/structural/sign.py
leglib-old/structural/snowcalc.py
leglib-old/structural/soil.py
leglib-old/structural/windcalc.py
leglib-old/structural/windcalc_other.py
leglib-old/structural/examples/__init__.py
leglib-old/structural/examples/pit_example.py
leglib-old/structural/examples/project_example.py
leglib-old/structural/examples/wind_other_structure_example.py
leglib-old/structural/tests/__init__.py
leglib-old/structural/tests/test_acibars.py
leglib-old/structural/tests/test_beamcolumn.py
leglib-old/structural/tests/test_buildingcode.py
leglib-old/structural/tests/test_conccol.py
leglib-old/structural/tests/test_concrete.py
leglib-old/structural/tests/test_driftcalc.py
leglib-old/structural/tests/test_embedment.py
leglib-old/structural/tests/test_equation.py
leglib-old/structural/tests/test_filters.py
leglib-old/structural/tests/test_footing.py
leglib-0.0.4.dist-info/LICENSE
leglib-0.0.4.dist-info/METADATA
leglib-0.0.4.dist-info/WHEEL
leglib-0.0.4.dist-info/top_level.txt
leglib-0.0.4.dist-info/RECORD
