Metadata-Version: 2.1
Name: leglib
Version: 0.0.4
Summary: My personal Python shared package with lots of weird stuff.
Home-page: https://github.com/joelegner/leglib
Author: Joe Legner
Author-email: joelegner@gmail.com
License: UNKNOWN
Platform: UNKNOWN
Classifier: Programming Language :: Python :: 3
Classifier: License :: OSI Approved :: MIT License
Classifier: Operating System :: OS Independent
Requires-Python: >=3.6
